{
  "/*404": [
    {
      "type": "script",
      "href": "/nurios/assets/_...404_-75e7e581.js"
    },
    {
      "type": "script",
      "href": "/nurios/assets/entry-client-a6165289.js"
    },
    {
      "type": "style",
      "href": "/nurios/assets/entry-client-ab9ddbb0.css"
    }
  ],
  "/": [
    {
      "type": "script",
      "href": "/nurios/assets/index-7119039d.js"
    },
    {
      "type": "script",
      "href": "/nurios/assets/entry-client-a6165289.js"
    },
    {
      "type": "style",
      "href": "/nurios/assets/entry-client-ab9ddbb0.css"
    }
  ],
  "entry-client": [
    {
      "type": "script",
      "href": "/nurios/assets/entry-client-a6165289.js"
    },
    {
      "type": "style",
      "href": "/nurios/assets/entry-client-ab9ddbb0.css"
    }
  ],
  "index.html": []
}